implicit_lambda/__init__.py
implicit_lambda/args_resolver.py
implicit_lambda/builtins.py
implicit_lambda/functools.py
implicit_lambda/itertools.py
implicit_lambda/details/codegen.py
implicit_lambda/details/collect_args.py
implicit_lambda/details/expression.py
implicit_lambda/details/glue.py
implicit_lambda/details/interpret.py
implicit_lambda/details/lambda_dsl.py
implicit_lambda/details/placeholders.py
implicit_lambda/tests/__init__.py
implicit_lambda/tests/test_args_resolver.py
implicit_lambda/tests/test_auto_lambdas.py
implicit_lambda/tests/test_codegen.py
implicit_lambda/tests/test_implicit_lambda.py
implicit_lambda/tests/test_ops.py
implicit_lambda/tests/test_performance.py
implicit_lambda/tests/test_placeholders.py
implicit_lambda/tests/test_special_ops.py
implicit_lambda-0.4.1.dist-info/licenses/LICENSE
implicit_lambda-0.4.1.dist-info/METADATA
implicit_lambda-0.4.1.dist-info/WHEEL
implicit_lambda-0.4.1.dist-info/top_level.txt
implicit_lambda-0.4.1.dist-info/RECORD
