Metadata-Version: 2.4
Name: implicit_lambda
Version: 0.4.1
Summary: Implicit lambdas with placeholder notation and code generation
Author-email: "Andreas @blackhc Kirsch" <blackhc+implicit_lambda@gmail.com>
License: MIT
Project-URL: Homepage, https://github.com/blackhc/implicit_lambda
Project-URL: Repository, https://github.com/blackhc/implicit_lambda
Keywords: tools,lambda,placeholder
Classifier: Development Status :: 3 - Alpha
Classifier: Intended Audience :: Developers
Classifier: Intended Audience :: Science/Research
Classifier: Topic :: Software Development :: Libraries :: Python Modules
Classifier: License :: OSI Approved :: MIT License
Classifier: Programming Language :: Python :: 3.8
Classifier: Programming Language :: Python :: 3.9
Classifier: Programming Language :: Python :: 3.10
Classifier: Programming Language :: Python :: 3.11
Classifier: Programming Language :: Python :: 3.12
Classifier: Programming Language :: Python :: 3.13
Requires-Python: >=3.8
License-File: LICENSE
Provides-Extra: dev
Requires-Dist: check-manifest; extra == "dev"
Provides-Extra: test
Requires-Dist: coverage; extra == "test"
Requires-Dist: codecov; extra == "test"
Requires-Dist: pytest; extra == "test"
Requires-Dist: pytest-benchmark; extra == "test"
Requires-Dist: pytest-cov; extra == "test"
Requires-Dist: hypothesis; extra == "test"
Dynamic: license-file
